dictionary/__init__.py
dictionary/dictionary.py
extremely_simple_dictionary-2.0.0.dist-info/METADATA
extremely_simple_dictionary-2.0.0.dist-info/WHEEL
extremely_simple_dictionary-2.0.0.dist-info/top_level.txt
extremely_simple_dictionary-2.0.0.dist-info/RECORD
