Metadata-Version: 2.1
Name: extremely-simple-dictionary
Version: 2.0.0
Summary: UNKNOWN
Author: Ertugrul Aktas
License: UNKNOWN
Platform: UNKNOWN
Requires-Python: >=3.8
Requires-Dist: requests (>=2.23.0)
